{"stats":{"minecraft:dropped":{"minecraft:netherite_hoe":1,"minecraft:spruce_wood":128,"minecraft:purple_stained_glass":10},"minecraft:killed":{"minecraft:skeleton":3,"minecraft:donkey":1,"minecraft:zombie":1,"minecraft:chicken":1},"minecraft:picked_up":{"minecraft:chicken":1,"minecraft:leather":2,"minecraft:grass_block":1,"minecraft:purple_stained_glass":10,"minecraft:bone":4,"minecraft:arrow":5,"minecraft:rotten_flesh":2,"minecraft:kelp":1,"minecraft:bow":1,"minecraft:wheat_seeds":20,"minecraft:spruce_wood":128,"minecraft:egg":1},"minecraft:custom":{"minecraft:time_since_rest":8640,"minecraft:walk_one_cm":37955,"minecraft:sprint_one_cm":25171,"minecraft:damage_taken":424,"minecraft:damage_absorbed":160,"minecraft:mob_kills":6,"minecraft:drop":76,"minecraft:damage_dealt":1571,"minecraft:interact_with_beacon":2,"minecraft:fly_one_cm":347483,"minecraft:crouch_one_cm":3825,"minecraft:play_time":142644,"minecraft:sneak_time":1727,"minecraft:walk_under_water_one_cm":9731,"minecraft:jump":192,"minecraft:leave_game":3,"minecraft:time_since_death":142644,"minecraft:walk_on_water_one_cm":15196,"minecraft:sleep_in_bed":2,"minecraft:total_world_time":142644,"minecraft:damage_resisted":99,"minecraft:fall_one_cm":2494,"minecraft:horse_one_cm":392},"minecraft:mined":{"minecraft:short_grass":81,"minecraft:tall_grass":9},"minecraft:used":{"minecraft:wooden_hoe":1,"minecraft:wooden_axe":10,"minecraft:netherite_sword":17,"minecraft:grass_block":50,"minecraft:netherite_hoe":14,"minecraft:zombie_spawn_egg":6,"minecraft:redstone_block":2,"minecraft:beacon":3,"minecraft:dirt":72,"minecraft:sand":3,"minecraft:white_bed":1,"minecraft:egg":1,"minecraft:enchanted_golden_apple":2}},"DataVersion":4189}